iranian_cities/__init__.py
iranian_cities/admin.py
iranian_cities/apps.py
iranian_cities/checks.py
iranian_cities/conf.py
iranian_cities/constants.py
iranian_cities/data/__init__.py
iranian_cities/data/city.csv
iranian_cities/data/county.csv
iranian_cities/data/district.csv
iranian_cities/data/province.csv
iranian_cities/data/rural_district.csv
iranian_cities/data/village.csv
iranian_cities/exc.py
iranian_cities/fields.py
iranian_cities/management/__init__.py
iranian_cities/management/commands/__init__.py
iranian_cities/management/commands/generate_city.py
iranian_cities/migrations/0001_initial.py
iranian_cities/migrations/0002_rename_shhahr_dehestan_shahr.py
iranian_cities/migrations/0003_remove_dehestan_shahr.py
iranian_cities/migrations/0004_remove_abadi_shhahr.py
iranian_cities/migrations/0005_auto_20221004_0004.py
iranian_cities/migrations/0006_alter_city_province_alter_county_province.py
iranian_cities/migrations/0007_alter_city_table_comment_alter_county_table_comment_and_more.py
iranian_cities/migrations/0008_alter_city_options_alter_county_options_and_more.py
iranian_cities/migrations/0009_rename_iranian_cit_code_1c3b38_idx_sage_city_code_8db749_idx_and_more.py
iranian_cities/migrations/__init__.py
iranian_cities/mixins/__init__.py
iranian_cities/mixins/base_inline.py
iranian_cities/mixins/base_location.py
iranian_cities/mixins/dynamic_permission.py
iranian_cities/models.py
django_iranian_cities-2.0.0.dist-info/LICENSE
django_iranian_cities-2.0.0.dist-info/METADATA
django_iranian_cities-2.0.0.dist-info/WHEEL
django_iranian_cities-2.0.0.dist-info/RECORD
