Metadata-Version: 2.1
Name: django-iranian-cities
Version: 2.0.0
Summary: Iranian cities support for Django
Home-page: https://github.com/sageteamorg/django-iranian-cities
License: GNU
Keywords: django,iranian,cities
Author: Sepehr Akbarzadeh
Author-email: sepehr@sageteam.org
Requires-Python: >=3.8,<4.0
Classifier: License :: Other/Proprietary License
Classifier: Programming Language :: Python :: 3
Classifier: Programming Language :: Python :: 3.8
Classifier: Programming Language :: Python :: 3.9
Classifier: Programming Language :: Python :: 3.10
Classifier: Programming Language :: Python :: 3.11
Classifier: Programming Language :: Python :: 3.12
Classifier: Programming Language :: Python :: 3.13
Requires-Dist: django (>=4.2,<5.0) ; python_version >= "3.8" and python_version < "3.10"
Requires-Dist: django (>=4.2,<5.3) ; python_version >= "3.10"
Project-URL: Issues, https://github.com/sageteamorg/django-iranian-cities/issues
Project-URL: Repository, https://github.com/sageteamorg/django-iranian-cities
Project-URL: Source Code, https://github.com/sageteamorg/django-iranian-cities
